{
    "final_space": true,
    "console_title": true,
    "console_title_style": "folder",
    "blocks": [
        {
            "type": "prompt",
            "alignment": "left",
            "horizontal_offset": 0,
            "vertical_offset": 0,
            "segments": [
                {
                    "type": "path",
                    "style": "diamond",
                    "powerline_symbol": "",
                    "invert_powerline": false,
                    "foreground": "#ffffff",
                    "background": "#529e90",
                    "leading_diamond": "",
                    "trailing_diamond": "",
                    "properties": {
                        "prefix": "  ",
                        "style": "folder"
                    }
                },
                {
                    "type": "git",
                    "style": "powerline",
                    "powerline_symbol": "",
                    "invert_powerline": false,
                    "foreground": "#ffffff",
                    "background": "#52869e",
                    "leading_diamond": "",
                    "trailing_diamond": "",
                    "properties": {
                        "display_status": true,
                        "display_stash_count": true,
                        "display_upstream_icon": true
                    }
                },
                {
                    "type": "executiontime",
                    "style": "diamond",
                    "leading_diamond": "<transparent,#529e6a>\ue0b0</>",
                    "trailing_diamond": "\ue0b0",
                    "foreground": "#ffffff",
                    "background": "#529e6a",
                    "properties": {
                        "style": "austin",
                        "threshold": 0
                    }
                }
            ]
        }
    ]
}